{"cameraMode":{"drawMode":0,"name":"Shaded","section":"Shading Mode"},"sceneLighting":true,"audioPlay":false,"sceneViewState":{"m_AlwaysRefresh":false,"showFog":true,"showSkybox":true,"showFlares":true,"showImageEffects":true,"showParticleSystems":true,"showVisualEffectGraphs":true,"m_FxEnabled":true},"in2DMode":false,"pivot":{"x":46.57561111450195,"y":2.834376335144043,"z":62.299285888671878},"rotation":{"x":0.06834516674280167,"y":0.001496029319241643,"z":-0.00010337021376471967,"w":0.9976639747619629},"size":5.999405860900879,"orthographic":false}